parcheck/__init__.py
parcheck/checker.py
parcheck/exceptions.py
parcheck/patterner.py
parcheck/static.py
parcheck/tools.py
parcheck-0.1.1.dist-info/LICENSE.txt
parcheck-0.1.1.dist-info/METADATA
parcheck-0.1.1.dist-info/WHEEL
parcheck-0.1.1.dist-info/top_level.txt
parcheck-0.1.1.dist-info/RECORD
