Metadata-Version: 2.1
Name: parcheck
Version: 0.1.1
Summary: A lightweight, minimalist, easy-to-use python toolkit
Home-page: https://github.com/Agwave/parcheck.git
Author: Agwave
Author-email: agwave@foxmail.com
Requires-Python: >=3
License-File: LICENSE.txt
